[
    {
        "id": 1,
        "title": "Гурме",
        "desc": "Пицца соус, маслины, пепперони, грибы, орегано",
        "url": "https://bellissimo.uz/_next/image?url=https%3A%2F%2Fio.bellissimo.uz%2Fimages%2Fd020eb98-5c57-43d6-ba90-969907dc8186.jpg&w=750&q=75",
        "price": 50000,
        "quantity": 0
    },
    {
        "id": 2,
        "title": "Супер Микс",
        "desc": "Пицца «Супер Микс» Сочетание 4х любимых вкусов в 1 пицце 😋 Отлично подойдёт для тех кто любит всё и сразу 🙃",
        "url": "https://bellissimo.uz/_next/image?url=https%3A%2F%2Fio.bellissimo.uz%2Fimages%2F94844930-5c66-4c12-a670-93b048169dbe.jpg&w=750&q=75",
        "price": 80000,
        "quantity": 0
    },
    {
        "id": 3,
        "title": "Сырный цыплёнок",
        "desc": "Нежное куриное филе, сыр моцарелла, томаты и сырный соус",
        "url": "https://bellissimo.uz/_next/image?url=https%3A%2F%2Fio.bellissimo.uz%2Fimages%2F17126e05-7876-45a6-be19-e6d0af0328a4.jpg&w=750&q=75",
        "price": 45000,
        "quantity": 0
    },
    {
        "id": 4,
        "title": "Чиккен карри",
        "desc": "Говяжий рулет и куриное филе в сочетании с сыром моцарелла, ананасами и соусом карри",
        "url": "https://bellissimo.uz/_next/image?url=https%3A%2F%2Fio.bellissimo.uz%2Fimages%2F45bd4064-2430-4250-899d-d6f834d36c30.jpg&w=750&q=75",
        "price": 50000,
        "quantity": 0
    },
    {
        "id": 5,
        "title": "Двойная пепперони",
        "desc": "Двойная порция пепперони в сочетании с сыром моцарелла под томатным соусом",
        "url": "https://bellissimo.uz/_next/image?url=https%3A%2F%2Fio.bellissimo.uz%2Fimages%2F23138748-1bff-4994-b42b-cf7044ed4e0d.jpg&w=750&q=75",
        "price": 54000,
        "quantity": 0
    },
    {
        "id": 6,
        "title": "Халапеньо",
        "desc": "Филе индейки, нежная говядина, лук шалот, томаты, пикантные перчики халапеньо, сыр Моцарелла и барбекю соус",
        "url": "https://bellissimo.uz/_next/image?url=https%3A%2F%2Fio.bellissimo.uz%2Fimages%2F84e3a554-551a-45f6-9ac1-9c7870aa6f14.jpg&w=750&q=75",
        "price": 50000,
        "quantity": 0
    },
    {
        "id": 7,
        "title": "Мексиканская",
        "desc": "Говяжий рулет, нежное куриное филе, острые перчики \"Халапеньо\", сыр \"Моцарелла\", барбекю соус",
        "url": "https://bellissimo.uz/_next/image?url=https%3A%2F%2Fio.bellissimo.uz%2Fimages%2F07b2af79-95e0-48ae-8962-3b29fdfcb6d4.jpg&w=750&q=75",
        "price": 50000,
        "quantity": 0
    },
    {
        "id": 8,
        "title": "Курица с грибами",
        "desc": "Куриное филе, сыр Моцарелла, грибы , орегано под соусом пицца",
        "url": "https://bellissimo.uz/_next/image?url=https%3A%2F%2Fio.bellissimo.uz%2Fimages%2F15f8411b-947d-405b-9c78-016711ba8da1.jpg&w=750&q=75",
        "price": 38000,
        "quantity": 0
    },
    {
        "id": 9,
        "title": "Беллиссимо",
        "desc": "Филе индейки, сыр Моцарелла, хрустящий болгарский перец, грибы, маслины и лук шалот под томатным соусом",
        "url": "https://bellissimo.uz/_next/image?url=https%3A%2F%2Fio.bellissimo.uz%2Fimages%2Fcd4ec26b-2bd5-4416-b50b-46e0f8ac5ed8.jpg&w=750&q=75",
        "price": 50000,
        "quantity": 0
    }
]